AUTHORS
LICENSE
MANIFEST.in
README.rst
setup.py
django_comments_xtd/__init__.py
django_comments_xtd/admin.py
django_comments_xtd/compat.py
django_comments_xtd/forms.py
django_comments_xtd/models.py
django_comments_xtd/signals.py
django_comments_xtd/signed.py
django_comments_xtd/urls.py
django_comments_xtd/utils.py
django_comments_xtd/views.py
django_comments_xtd/conf/__init__.py
django_comments_xtd/conf/defaults.py
django_comments_xtd/migrations/0001_initial.py
django_comments_xtd/migrations/0002_auto__add_field_xtdcomment_thread__add_field_xtdcomment_parent__add_fi.py
django_comments_xtd/migrations/0003_threads.py
django_comments_xtd/migrations/__init__.py
django_comments_xtd/templates/404.html
django_comments_xtd/templates/django_comments_xtd/comment.html
django_comments_xtd/templates/django_comments_xtd/discarded.html
django_comments_xtd/templates/django_comments_xtd/email_confirmation_request.html
django_comments_xtd/templates/django_comments_xtd/email_confirmation_request.txt
django_comments_xtd/templates/django_comments_xtd/email_followup_comment.html
django_comments_xtd/templates/django_comments_xtd/email_followup_comment.txt
django_comments_xtd/templates/django_comments_xtd/max_thread_level.html
django_comments_xtd/templates/django_comments_xtd/muted.html
django_comments_xtd/templates/django_comments_xtd/reply.html
django_comments_xtd/templatetags/__init__.py
django_comments_xtd/templatetags/comments_xtd.py
django_comments_xtd/tests/__init__.py
django_comments_xtd/tests/forms.py
django_comments_xtd/tests/models.py
django_comments_xtd/tests/templatetags.py
django_comments_xtd/tests/urls.py
django_comments_xtd/tests/views.py
django_comments_xtd_thelab.egg-info/PKG-INFO
django_comments_xtd_thelab.egg-info/SOURCES.txt
django_comments_xtd_thelab.egg-info/dependency_links.txt
django_comments_xtd_thelab.egg-info/top_level.txt
docs/Makefile
docs/conf.py
docs/example.rst
docs/index.rst
docs/make.bat
docs/settings.rst
docs/templates.rst
docs/templatetags.rst
docs/tutorial.rst
tests/__init__.py
tests/runtests.py
tests/settings.py