Metadata-Version: 1.1
Name: django-comments-xtd-thelab
Version: 1.3a1
Summary: Django Comments Framework extension app with thread support, follow up notifications and email confirmations.
Home-page: http://pypi.python.org/pypi/django-comments-xtd
Author: Daniel Rus Morales
Author-email: inbox@danir.us
License: MIT
Platform: UNKNOWN
Classifier: Development Status :: 4 - Beta
Classifier: Environment :: Web Environment
Classifier: Intended Audience :: Developers
Classifier: License :: OSI Approved :: MIT License
Classifier: Operating System :: OS Independent
Classifier: Programming Language :: Python
Classifier: Programming Language :: Python :: 3
Classifier: Framework :: Django
Classifier: Natural Language :: English
Classifier: Topic :: Internet :: WWW/HTTP :: Dynamic Content :: News/Diary
